incenp/__init__.py
incenp/click_shell/__init__.py
incenp/click_shell/_cmd.py
incenp/click_shell/_compat.py
incenp/click_shell/core.py
incenp.click_shell-2.1.0.dist-info/AUTHORS
incenp.click_shell-2.1.0.dist-info/LICENSE
incenp.click_shell-2.1.0.dist-info/METADATA
incenp.click_shell-2.1.0.dist-info/WHEEL
incenp.click_shell-2.1.0.dist-info/top_level.txt
incenp.click_shell-2.1.0.dist-info/RECORD
